{"tasks":[{"id":"8280f38e-385d-4c9e-974d-3369be660bb4","title":"dominar o universo","description":"Descrição alterada","completedAt":null,"createdAt":"2023-10-20T21:10:03.038Z","updatedAt":"2023-10-20T21:21:15.071Z"},{"id":"ef2acd83-8109-4cd3-9293-6be07c8a5c88","title":"oioioiio","description":" tchau tchau tchau","completedAt":null,"createdAt":"2023-10-20T21:10:03.041Z","updatedAt":"2023-10-20T21:10:03.041Z"},{"id":"2e9513b0-ac75-4c0e-9d86-e580f384e0a6","title":"Fazer camarão no abacaxi","description":" comer comer comer","completedAt":null,"createdAt":"2023-10-20T21:56:38.969Z","updatedAt":"2023-10-20T21:56:38.969Z"},{"id":"72985d00-b704-42dd-b225-8feee0d80479","title":"Estudar POO","description":" com java toper topissimo","completedAt":null,"createdAt":"2023-10-20T21:56:38.978Z","updatedAt":"2023-10-20T21:56:38.978Z"},{"id":"44277fe5-8154-455e-8f84-5178b11f252c","title":"Estudar node","description":" uhuuum javascript mais toper ainda","completedAt":null,"createdAt":"2023-10-20T21:56:38.982Z","updatedAt":"2023-10-20T21:56:38.982Z"},{"id":"d7e7bc78-b707-41db-9ce7-f1ed3d29ad31","title":"faculdade","description":" não toper ","completedAt":null,"createdAt":"2023-10-20T21:56:38.986Z","updatedAt":"2023-10-20T21:56:38.986Z"}]}